amtrak/__init__.py
amtrak/__main__.py
amtrak-0.0.1.dist-info/METADATA
amtrak-0.0.1.dist-info/WHEEL
amtrak-0.0.1.dist-info/top_level.txt
amtrak-0.0.1.dist-info/RECORD
